alu.v
// alu.v
module alu(
  input  wire [7:0] a,
  input  wire [7:0] b,
  input  wire [3:0] op,   // 0000=PASSA, 0001=PASSB, 0010=ADD, 0011=SUB,
                          // 0100=AND, 0101=OR, 0110=XOR, 0111=NOTA,
                          // 1000=SHL_A, 1001=SHR_A, 1010=INC_B
  output reg  [7:0] y,
  output wire z, n,
  output reg  c, v
);
  reg [8:0] tmp;

  always @* begin
    y = 8'h00; c = 1'b0; v = 1'b0;
    case (op)
      4'h0: y = a;                 // PASS A
      4'h1: y = b;                 // PASS B
      4'h2: begin                  // ADD
        tmp = {1'b0,a} + {1'b0,b};
        y   = tmp[7:0];
        c   = tmp[8];
        v   = (~(a[7]^b[7]) & (a[7]^y[7]));
      end
      4'h3: begin                  // SUB = a - b
        tmp = {1'b0,a} + {1'b0,~b} + 9'd1;
        y   = tmp[7:0];
        c   = tmp[8];              // ~borrow
        v   = ((a[7]^b[7]) & (a[7]^y[7]));
      end
      4'h4: y = a & b;             // AND
      4'h5: y = a | b;             // OR
      4'h6: y = a ^ b;             // XOR
      4'h7: y = ~a;                // NOT (sobre 'a')
      4'h8: begin                  // SHL (sobre 'a')
        y = {a[6:0],1'b0};
        c = a[7];
      end
      4'h9: begin                  // SHR (lógico, sobre 'a')
        y = {1'b0,a[7:1]};
        c = a[0];
      end
      4'hA: begin                  // INC B (usa 'b')
        tmp = {1'b0,b} + 9'd1;
        y   = tmp[7:0];
        c   = tmp[8];
        v   = (~b[7]) & y[7];
      end
      default: y = 8'h00;
    endcase
  end

  assign z = (y == 8'h00);
  assign n = y[7];
endmodule

src/computer/register.v
// register.v
module register #(parameter W=8)(
  input  wire           clk,
  input  wire           rst,
  input  wire           we,
  input  wire [W-1:0]   d,
  output reg  [W-1:0]   q
);
  always @(posedge clk or posedge rst) begin
    if (rst) q <= {W{1'b0}};
    else if (we) q <= d;
  end
endmodule

instruction_memory.v
// instruction_memory.v  -- Formato 7+8 en 15 bits (bit 15 no usado)
// Lee BINARIO puro (16 bits por línea) desde im.dat
module instruction_memory(
  input  wire [15:0] address,
  output wire [14:0] out
);
  reg [15:0] mem [0:65535];

  initial begin
    $readmemb("im.dat", mem);   // <--- BINARIO
    // Log para verificar carga (aparece una sola vez en consola)
    $display("[IMEM] mem[0]=%b mem[1]=%b", mem[0], mem[1]);
  end

  // Entregamos los 15 bits válidos: [14:8]=opcode (7b), [7:0]=imm (8b)
  assign out = mem[address][14:0];
endmodule

pc.v
// pc.v
module pc(
  input  wire        clk,
  input  wire        rst,
  input  wire [15:0] next_pc,
  output reg  [15:0] pc
);
  // Evita PC='x' al inicio de la simulación
  initial pc = 16'h0000;

  always @(posedge clk or posedge rst) begin
    if (rst) pc <= 16'h0000;
    else     pc <= next_pc;
  end
endmodule

computer.v
// computer.v  -- ISA 7+8 (15 bits) | A/B de 8 bits | Básicas completas
module computer(
  input  wire clk,
  input  wire rst
);
  // ===== PC & Fetch =====
  wire [15:0] pc_curr;
  wire [15:0] pc_next = pc_curr + 16'd1;
  wire [14:0] ir15;

  pc U_PC(.clk(clk), .rst(rst), .next_pc(pc_next), .pc(pc_curr));
  instruction_memory U_IM(.address(pc_curr), .out(ir15));

  // Campos
  wire [6:0] opcode = ir15[14:8];
  wire [7:0] imm    = ir15[7:0];

  // ===== Registros A/B =====
  wire [7:0] A_q, B_q;
  reg        weA, weB;
  wire [7:0] Y;

  register #(8) U_RA(.clk(clk), .rst(rst), .we(weA), .d(Y), .q(A_q));
  register #(8) U_RB(.clk(clk), .rst(rst), .we(weB), .d(Y), .q(B_q));

  // ===== Control =====
  // selX: 00->A, 01->B, 10->IMM (para alimentar 'a' o 'b' según operación)
  reg [1:0] selA, selB;
  reg [3:0] alu_op;

  // Banderas
  wire Z, N, C_from_alu, V_from_alu;
  reg  Zf, Nf, Cf, Vf;

  // Evita 'x' iniciales en flags
  initial begin Zf=1'b0; Nf=1'b0; Cf=1'b0; Vf=1'b0; end

  // Operandos a la ALU
  wire [7:0] opA = (selA==2'b00) ? A_q : (selA==2'b01 ? B_q : imm);
  wire [7:0] opB = (selB==2'b00) ? A_q : (selB==2'b01 ? B_q : imm);

  alu U_ALU(.a(opA), .b(opB), .op(alu_op), .y(Y), .z(Z), .n(N), .c(C_from_alu), .v(V_from_alu));

  // Decodificación (TODAS las básicas)
  always @* begin
    // defaults
    weA=0; weB=0;
    selA=2'b00; selB=2'b01; // por defecto: a=A, b=B
    alu_op=4'h0;            // PASSA

    case (opcode)
      // MOV
      7'h00: begin // MOV A,B
        alu_op=4'h1; selA=2'b01; weA=1;
      end
      7'h01: begin // MOV B,A
        alu_op=4'h0; selB=2'b00; weB=1;
      end
      7'h02: begin // MOV A, lit
        selA=2'b10; weA=1;      // Y = imm
      end
      7'h03: begin // MOV B, lit
        selB=2'b10; weB=1;      // Y = imm (vía PASSB si quisieras, aquí sirve PASSA con a=imm)
      end

      // ADD
      7'h04: begin // ADD A,B
        alu_op=4'h2; selA=2'b00; selB=2'b01; weA=1;
      end
      7'h05: begin // ADD B,A
        alu_op=4'h2; selA=2'b01; selB=2'b00; weB=1;
      end
      7'h06: begin // ADD A, lit
        alu_op=4'h2; selA=2'b00; selB=2'b10; weA=1;
      end
      7'h07: begin // ADD B, lit
        alu_op=4'h2; selA=2'b01; selB=2'b10; weB=1;
      end

      // SUB
      7'h08: begin // SUB A,B
        alu_op=4'h3; selA=2'b00; selB=2'b01; weA=1;
      end
      7'h09: begin // SUB B,A
        alu_op=4'h3; selA=2'b01; selB=2'b00; weB=1;
      end
      7'h0A: begin // SUB A, lit
        alu_op=4'h3; selA=2'b00; selB=2'b10; weA=1;
      end
      7'h0B: begin // SUB B, lit
        alu_op=4'h3; selA=2'b01; selB=2'b10; weB=1;
      end

      // AND
      7'h0C: begin // AND A,B
        alu_op=4'h4; selA=2'b00; selB=2'b01; weA=1;
      end
      7'h0D: begin // AND B,A
        alu_op=4'h4; selA=2'b01; selB=2'b00; weB=1;
      end
      7'h0E: begin // AND A, lit
        alu_op=4'h4; selA=2'b00; selB=2'b10; weA=1;
      end
      7'h0F: begin // AND B, lit
        alu_op=4'h4; selA=2'b01; selB=2'b10; weB=1;
      end

      // OR
      7'h10: begin // OR A,B
        alu_op=4'h5; selA=2'b00; selB=2'b01; weA=1;
      end
      7'h11: begin // OR B,A
        alu_op=4'h5; selA=2'b01; selB=2'b00; weB=1;
      end
      7'h12: begin // OR A, lit
        alu_op=4'h5; selA=2'b00; selB=2'b10; weA=1;
      end
      7'h13: begin // OR B, lit
        alu_op=4'h5; selA=2'b01; selB=2'b10; weB=1;
      end

      // NOT
      7'h14: begin // NOT A,A  -> A = ~A
        alu_op=4'h7; selA=2'b00; weA=1;
      end
      7'h15: begin // NOT A,B  -> A = ~B
        alu_op=4'h7; selA=2'b01; weA=1;
      end
      7'h16: begin // NOT B,A  -> B = ~A
        alu_op=4'h7; selA=2'b00; weB=1;
      end
      7'h17: begin // NOT B,B  -> B = ~B
        alu_op=4'h7; selA=2'b01; weB=1;
      end

      // XOR
      7'h18: begin // XOR A,B
        alu_op=4'h6; selA=2'b00; selB=2'b01; weA=1;
      end
      7'h19: begin // XOR B,A
        alu_op=4'h6; selA=2'b01; selB=2'b00; weB=1;
      end
      7'h1A: begin // XOR A, lit
        alu_op=4'h6; selA=2'b00; selB=2'b10; weA=1;
      end
      7'h1B: begin // XOR B, lit
        alu_op=4'h6; selA=2'b01; selB=2'b10; weB=1;
      end

      // SHL (ALU desplaza 'a')
      7'h1C: begin // SHL A,A
        alu_op=4'h8; selA=2'b00; weA=1;
      end
      7'h1D: begin // SHL A,B  -> A = B<<1
        alu_op=4'h8; selA=2'b01; weA=1;
      end
      7'h1E: begin // SHL B,A  -> B = A<<1
        alu_op=4'h8; selA=2'b00; weB=1;
      end
      7'h1F: begin // SHL B,B
        alu_op=4'h8; selA=2'b01; weB=1;
      end

      // SHR (ALU desplaza 'a' lógico)
      7'h20: begin // SHR A,A
        alu_op=4'h9; selA=2'b00; weA=1;
      end
      7'h21: begin // SHR A,B  -> A = B>>1
        alu_op=4'h9; selA=2'b01; weA=1;
      end
      7'h22: begin // SHR B,A  -> B = A>>1
        alu_op=4'h9; selA=2'b00; weB=1;
      end
      7'h23: begin // SHR B,B
        alu_op=4'h9; selA=2'b01; weB=1;
      end

      // INC
      7'h24: begin // INC B
        alu_op=4'hA; selA=2'b00; selB=2'b01; weB=1;
      end

      default: ; // NOP
    endcase
  end

  // Latch de banderas al escribir A o B
  always @(posedge clk or posedge rst) begin
    if (rst) begin
      {Zf,Nf,Cf,Vf} <= 4'b0000;
    end else if (weA || weB) begin
      Zf <= Z; Nf <= N; Cf <= C_from_alu; Vf <= V_from_alu;
    end
  end

  // ===== Señales de debug para GTKWave =====
  // synthesis translate_off
  wire [6:0]  opcode_dbg = opcode;
  wire [7:0]  imm_dbg    = imm;
  wire [7:0]  A_dbg      = A_q;
  wire [7:0]  B_dbg      = B_q;
  wire [7:0]  Y_dbg      = Y;
  wire        Z_dbg      = Zf, N_dbg = Nf, C_dbg = Cf, V_dbg = Vf;
  wire [15:0] pc_dbg     = pc_curr;
  // synthesis translate_on
endmodule

testbench.v
// testbench.v
`timescale 1ns/1ps
module testbench;
  reg clk = 0, rst = 1;

  computer DUT(.clk(clk), .rst(rst));

  // clock 10 ns (100 MHz)
  always #5 clk = ~clk;

  initial begin
    $dumpfile("out/dump.vcd");
    $dumpvars(0, testbench);

    // Reset firme por ~5 ciclos
    rst = 1;
    repeat (10) @(posedge clk);  // ~100 ns
    rst = 0;

    // Corre un rato y termina
    repeat (400) @(posedge clk);
    $finish;
  end
endmodule

out/dump.vcd
$date
	Tue Sep 30 21:42:11 2025
$end
$version
	Icarus Verilog
$end
$timescale
	1ps
$end
$scope module testbench $end
$var reg 1 ! clk $end
$var reg 1 " rst $end
$scope module DUT $end
$var wire 8 # A_dbg [7:0] $end
$var wire 8 $ B_dbg [7:0] $end
$var wire 1 % C_dbg $end
$var wire 1 & N_dbg $end
$var wire 1 ' V_dbg $end
$var wire 8 ( Y_dbg [7:0] $end
$var wire 1 ) Z_dbg $end
$var wire 1 ! clk $end
$var wire 8 * imm_dbg [7:0] $end
$var wire 7 + opcode_dbg [6:0] $end
$var wire 16 , pc_dbg [15:0] $end
$var wire 1 " rst $end
$var wire 16 - pc_next [15:0] $end
$var wire 16 . pc_curr [15:0] $end
$var wire 7 / opcode [6:0] $end
$var wire 8 0 opB [7:0] $end
$var wire 8 1 opA [7:0] $end
$var wire 15 2 ir15 [14:0] $end
$var wire 8 3 imm [7:0] $end
$var wire 1 4 Z $end
$var wire 8 5 Y [7:0] $end
$var wire 1 6 V_from_alu $end
$var wire 1 7 N $end
$var wire 1 8 C_from_alu $end
$var wire 8 9 B_q [7:0] $end
$var wire 8 : A_q [7:0] $end
$var reg 1 ; Cf $end
$var reg 1 < Nf $end
$var reg 1 = Vf $end
$var reg 1 > Zf $end
$var reg 4 ? alu_op [3:0] $end
$var reg 2 @ selA [1:0] $end
$var reg 2 A selB [1:0] $end
$var reg 1 B weA $end
$var reg 1 C weB $end
$scope module U_ALU $end
$var wire 8 D a [7:0] $end
$var wire 8 E b [7:0] $end
$var wire 4 F op [3:0] $end
$var wire 1 4 z $end
$var wire 1 7 n $end
$var reg 1 8 c $end
$var reg 9 G tmp [8:0] $end
$var reg 1 6 v $end
$var reg 8 H y [7:0] $end
$upscope $end
$scope module U_IM $end
$var wire 15 I out [14:0] $end
$var wire 16 J address [15:0] $end
$upscope $end
$scope module U_PC $end
$var wire 1 ! clk $end
$var wire 16 K next_pc [15:0] $end
$var wire 1 " rst $end
$var reg 16 L pc [15:0] $end
$upscope $end
$scope module U_RA $end
$var wire 1 ! clk $end
$var wire 8 M d [7:0] $end
$var wire 1 " rst $end
$var wire 1 B we $end
$var parameter 32 N W $end
$var reg 8 O q [7:0] $end
$upscope $end
$scope module U_RB $end
$var wire 1 ! clk $end
$var wire 8 P d [7:0] $end
$var wire 1 " rst $end
$var wire 1 C we $end
$var parameter 32 Q W $end
$var reg 8 R q [7:0] $end
$upscope $end
$upscope $end
$upscope $end
$enddefinitions $end
$comment Show the parameter values. $end
$dumpall
b1000 Q
b1000 N
$end
#0
$dumpvars
bx R
b10010 P
bx O
b10010 M
b0 L
b1 K
b0 J
b1000010010 I
b10010 H
bx G
b0 F
bx E
b10010 D
0C
1B
b1 A
b10 @
b0 ?
0>
0=
0<
0;
bx :
bx 9
08
07
06
b10010 5
04
b10010 3
b1000010010 2
b10010 1
bx 0
b10 /
b0 .
b1 -
b0 ,
b10 +
b10010 *
0)
b10010 (
0'
0&
0%
bx $
bx #
1"
0!
$end
#5000
04
b10010 (
b10010 5
b10010 H
b10010 M
b10010 P
b0 0
b0 E
b0 #
b0 :
b0 O
b0 $
b0 9
b0 R
1!
#10000
0!
#15000
1!
#20000
0!
#25000
1!
#30000
0!
#35000
1!
#40000
0!
#45000
1!
#50000
0!
#55000
1!
#60000
0!
#65000
1!
#70000
0!
#75000
1!
#80000
0!
#85000
1!
#90000
0!
#95000
04
b10010 (
b10010 5
b10010 H
b10010 M
b10010 P
b110100 0
b110100 E
1C
b10 A
b0 @
0B
b110100 *
b110100 3
b11 +
b11 /
b1100110100 2
b1100110100 I
b10010 #
b10010 :
b10010 O
b10 -
b10 K
b1 ,
b1 .
b1 J
b1 L
0"
1!
#100000
0!
#105000
b10010 0
b10010 E
04
b10010 (
b10010 5
b10010 H
b10010 M
b10010 P
1B
b1 @
b1 ?
b1 F
b1 A
0C
b0 *
b0 3
b0 +
b0 /
b0 2
b0 I
b11 -
b11 K
b10 ,
b10 .
b10 J
b10 L
b10010 $
b10010 9
b10010 R
1!
#110000
0!
#115000
04
b10010 (
b10010 5
b10010 H
b10010 M
b10010 P
1C
b0 A
b0 ?
b0 F
b0 @
0B
b1 +
b1 /
b100000000 2
b100000000 I
b100 -
b100 K
b11 ,
b11 .
b11 J
b11 L
1!
#120000
0!
#125000
b100100 G
04
b100100 (
b100100 5
b100100 H
b100100 M
b100100 P
1B
b10 ?
b10 F
b1 A
0C
b100 +
b100 /
b10000000000 2
b10000000000 I
b101 -
b101 K
b100 ,
b100 .
b100 J
b100 L
1!
#130000
0!
#135000
b100100 0
b100100 E
1C
b0 A
b1 @
b10 ?
b10 F
0B
b110110 G
04
b110110 (
b110110 5
b110110 H
b110110 M
b110110 P
b101 +
b101 /
b10010 1
b10010 D
b10100000000 2
b10100000000 I
b100100 #
b100100 :
b100100 O
b110 -
b110 K
b101 ,
b101 .
b101 J
b101 L
1!
#140000
0!
#145000
b101 0
b101 E
1B
b10 ?
b10 F
b10 A
b0 @
0C
b101001 G
04
b101001 (
b101001 5
b101001 H
b101001 M
b101001 P
b101 *
b101 3
b110 +
b110 /
b100100 1
b100100 D
b11000000101 2
b11000000101 I
b111 -
b111 K
b110 ,
b110 .
b110 J
b110 L
b110110 $
b110110 9
b110110 R
1!
#150000
0!
#155000
b111 0
b111 E
1C
b1 @
b10 ?
b10 F
b10 A
0B
b111101 G
04
b111101 (
b111101 5
b111101 H
b111101 M
b111101 P
b111 *
b111 3
b111 +
b111 /
b110110 1
b110110 D
b11100000111 2
b11100000111 I
b101001 #
b101001 :
b101001 O
b1000 -
b1000 K
b111 ,
b111 .
b111 J
b111 L
1!
#160000
0!
#165000
17
b111101 0
b111101 E
08
1B
b11 ?
b11 F
b1 A
b0 @
0C
b11101100 G
04
b11101100 (
b11101100 5
b11101100 H
b11101100 M
b11101100 P
b0 *
b0 3
b1000 +
b1000 /
b101001 1
b101001 D
b100000000000 2
b100000000000 I
b1001 -
b1001 K
b1000 ,
b1000 .
b1000 J
b1000 L
b111101 $
b111101 9
b111101 R
1!
#170000
0!
#175000
07
b11101100 0
b11101100 E
1C
b0 A
b1 @
b11 ?
b11 F
0B
08
b1010001 G
04
b1010001 (
b1010001 5
b1010001 H
b1010001 M
b1010001 P
b1001 +
b1001 /
b111101 1
b111101 D
b100100000000 2
b100100000000 I
1&
1<
b11101100 #
b11101100 :
b11101100 O
b1010 -
b1010 K
b1001 ,
b1001 .
b1001 J
b1001 L
1!
#180000
0!
#185000
17
18
b10000 0
b10000 E
1B
b11 ?
b11 F
b10 A
b0 @
0C
b111011100 G
04
b11011100 (
b11011100 5
b11011100 H
b11011100 M
b11011100 P
b10000 *
b10000 3
b1010 +
b1010 /
b11101100 1
b11101100 D
b101000010000 2
b101000010000 I
b1011 -
b1011 K
b1010 ,
b1010 .
b1010 J
b1010 L
b1010001 $
b1010001 9
b1010001 R
0&
0<
1!
#190000
0!
#195000
07
b100000 0
b100000 E
1C
b1 @
b11 ?
b11 F
b10 A
0B
b100110001 G
18
04
b110001 (
b110001 5
b110001 H
b110001 M
b110001 P
b100000 *
b100000 3
b1011 +
b1011 /
b1010001 1
b1010001 D
b101100100000 2
b101100100000 I
1%
1;
1&
1<
b11011100 #
b11011100 :
b11011100 O
b1100 -
b1100 K
b1011 ,
b1011 .
b1011 J
b1011 L
1!
#200000
0!
#205000
b110001 0
b110001 E
1B
b100 ?
b100 F
b1 A
b0 @
0C
b100010001 G
08
04
b10000 (
b10000 5
b10000 H
b10000 M
b10000 P
b0 *
b0 3
b1100 +
b1100 /
b11011100 1
b11011100 D
b110000000000 2
b110000000000 I
b1101 -
b1101 K
b1100 ,
b1100 .
b1100 J
b1100 L
b110001 $
b110001 9
b110001 R
0&
0<
1!
#210000
0!
#215000
b10000 0
b10000 E
1C
b0 A
b1 @
b100 ?
b100 F
0B
04
b10000 (
b10000 5
b10000 H
b10000 M
b10000 P
b1101 +
b1101 /
b110001 1
b110001 D
b110100000000 2
b110100000000 I
0%
0;
b10000 #
b10000 :
b10000 O
b1110 -
b1110 K
b1101 ,
b1101 .
b1101 J
b1101 L
1!
#220000
0!
#225000
b11110000 0
b11110000 E
1B
b100 ?
b100 F
b10 A
b0 @
0C
04
b10000 (
b10000 5
b10000 H
b10000 M
b10000 P
b11110000 *
b11110000 3
b1110 +
b1110 /
b10000 1
b10000 D
b111011110000 2
b111011110000 I
b1111 -
b1111 K
b1110 ,
b1110 .
b1110 J
b1110 L
b10000 $
b10000 9
b10000 R
1!
#230000
0!
#235000
b1111 0
b1111 E
14
b0 (
b0 5
b0 H
b0 M
b0 P
1C
b1 @
b100 ?
b100 F
b10 A
0B
b1111 *
b1111 3
b1111 +
b1111 /
b111100001111 2
b111100001111 I
b10000 -
b10000 K
b1111 ,
b1111 .
b1111 J
b1111 L
1!
#240000
0!
#245000
b0 0
b0 E
04
b1000 (
b1000 5
b1000 H
b1000 M
b1000 P
1B
b1001 ?
b1001 F
b1 A
b0 @
0C
b0 *
b0 3
b100000 +
b100000 /
b10000 1
b10000 D
b10000000000000 2
b10000000000000 I
b10001 -
b10001 K
b10000 ,
b10000 .
b10000 J
b10000 L
b0 $
b0 9
b0 R
1)
1>
1!
#250000
0!
#255000
b1 @
b1001 ?
b1001 F
1B
14
b0 (
b0 5
b0 H
b0 M
b0 P
b100001 +
b100001 /
b0 1
b0 D
b10000100000000 2
b10000100000000 I
0)
0>
b1000 #
b1000 :
b1000 O
b10010 -
b10010 K
b10001 ,
b10001 .
b10001 J
b10001 L
1!
#260000
0!
#265000
04
b1 (
b1 5
b1 H
b1 M
b1 P
b1 G
1C
b1010 ?
b1010 F
b0 @
0B
b1010101 *
b1010101 3
b100100 +
b100100 /
b10010001010101 2
b10010001010101 I
b10011 -
b10011 K
b10010 ,
b10010 .
b10010 J
b10010 L
b0 #
b0 :
b0 O
1)
1>
1!
#270000
0!
#275000
14
b0 (
b0 5
b0 H
b0 M
b0 P
b0 ?
b0 F
0C
b1 0
b1 E
b10101010 *
b10101010 3
b100111 +
b100111 /
b10011110101010 2
b10011110101010 I
0)
0>
b1 $
b1 9
b1 R
b10100 -
b10100 K
b10011 ,
b10011 .
b10011 J
b10011 L
1!
#280000
0!
#285000
b0 *
b0 3
b101000 +
b101000 /
b10100000000000 2
b10100000000000 I
b10101 -
b10101 K
b10100 ,
b10100 .
b10100 J
b10100 L
1!
#290000
0!
#295000
b101010 +
b101010 /
b10101000000000 2
b10101000000000 I
b10110 -
b10110 K
b10101 ,
b10101 .
b10101 J
b10101 L
1!
#300000
0!
#305000
b101100 +
b101100 /
b10110000000000 2
b10110000000000 I
b10111 -
b10111 K
b10110 ,
b10110 .
b10110 J
b10110 L
1!
#310000
0!
#315000
b101110 +
b101110 /
b10111000000000 2
b10111000000000 I
b11000 -
b11000 K
b10111 ,
b10111 .
b10111 J
b10111 L
1!
#320000
0!
#325000
b110000 +
b110000 /
b11000000000000 2
b11000000000000 I
b11001 -
b11001 K
b11000 ,
b11000 .
b11000 J
b11000 L
1!
#330000
0!
#335000
b110001 +
b110001 /
b11000100000000 2
b11000100000000 I
b11010 -
b11010 K
b11001 ,
b11001 .
b11001 J
b11001 L
1!
#340000
0!
#345000
b11111111 *
b11111111 3
b110100 +
b110100 /
b11010011111111 2
b11010011111111 I
b11011 -
b11011 K
b11010 ,
b11010 .
b11010 J
b11010 L
1!
#350000
0!
#355000
b1111 *
b1111 3
b110110 +
b110110 /
b11011000001111 2
b11011000001111 I
b11100 -
b11100 K
b11011 ,
b11011 .
b11011 J
b11011 L
1!
#360000
0!
#365000
b0 *
b0 3
b111000 +
b111000 /
b11100000000000 2
b11100000000000 I
b11101 -
b11101 K
b11100 ,
b11100 .
b11100 J
b11100 L
1!
#370000
0!
#375000
b111001 +
b111001 /
b11100100000000 2
b11100100000000 I
b11110 -
b11110 K
b11101 ,
b11101 .
b11101 J
b11101 L
1!
#380000
0!
#385000
b111010 +
b111010 /
b11101000000000 2
b11101000000000 I
b11111 -
b11111 K
b11110 ,
b11110 .
b11110 J
b11110 L
1!
#390000
0!
#395000
b111011 +
b111011 /
b11101100000000 2
b11101100000000 I
b100000 -
b100000 K
b11111 ,
b11111 .
b11111 J
b11111 L
1!
#400000
0!
#405000
b1000000 +
b1000000 /
b100000000000000 2
b100000000000000 I
b100001 -
b100001 K
b100000 ,
b100000 .
b100000 J
b100000 L
1!
#410000
0!
#415000
b1000001 +
b1000001 /
b100000100000000 2
b100000100000000 I
b100010 -
b100010 K
b100001 ,
b100001 .
b100001 J
b100001 L
1!
#420000
0!
#425000
b1000010 +
b1000010 /
b100001000000000 2
b100001000000000 I
b100011 -
b100011 K
b100010 ,
b100010 .
b100010 J
b100010 L
1!
#430000
0!
#435000
b1000011 +
b1000011 /
b100001100000000 2
b100001100000000 I
b100100 -
b100100 K
b100011 ,
b100011 .
b100011 J
b100011 L
1!
#440000
0!
#445000
b1001000 +
b1001000 /
b100100000000000 2
b100100000000000 I
b100101 -
b100101 K
b100100 ,
b100100 .
b100100 J
b100100 L
1!
#450000
0!
#455000
bx *
bx 3
bx +
bx /
bx 2
bx I
b100110 -
b100110 K
b100101 ,
b100101 .
b100101 J
b100101 L
1!
#460000
0!
#465000
b100111 -
b100111 K
b100110 ,
b100110 .
b100110 J
b100110 L
1!
#470000
0!
#475000
b101000 -
b101000 K
b100111 ,
b100111 .
b100111 J
b100111 L
1!
#480000
0!
#485000
b101001 -
b101001 K
b101000 ,
b101000 .
b101000 J
b101000 L
1!
#490000
0!
#495000
b101010 -
b101010 K
b101001 ,
b101001 .
b101001 J
b101001 L
1!
#500000
0!
#505000
b101011 -
b101011 K
b101010 ,
b101010 .
b101010 J
b101010 L
1!
#510000
0!
#515000
b101100 -
b101100 K
b101011 ,
b101011 .
b101011 J
b101011 L
1!
#520000
0!
#525000
b101101 -
b101101 K
b101100 ,
b101100 .
b101100 J
b101100 L
1!
#530000
0!
#535000
b101110 -
b101110 K
b101101 ,
b101101 .
b101101 J
b101101 L
1!
#540000
0!
#545000
b101111 -
b101111 K
b101110 ,
b101110 .
b101110 J
b101110 L
1!
#550000
0!
#555000
b110000 -
b110000 K
b101111 ,
b101111 .
b101111 J
b101111 L
1!
#560000
0!
#565000
b110001 -
b110001 K
b110000 ,
b110000 .
b110000 J
b110000 L
1!
#570000
0!
#575000
b110010 -
b110010 K
b110001 ,
b110001 .
b110001 J
b110001 L
1!
#580000
0!
#585000
b110011 -
b110011 K
b110010 ,
b110010 .
b110010 J
b110010 L
1!
#590000
0!
#595000
b110100 -
b110100 K
b110011 ,
b110011 .
b110011 J
b110011 L
1!
#600000
0!
#605000
b110101 -
b110101 K
b110100 ,
b110100 .
b110100 J
b110100 L
1!
#610000
0!
#615000
b110110 -
b110110 K
b110101 ,
b110101 .
b110101 J
b110101 L
1!
#620000
0!
#625000
b110111 -
b110111 K
b110110 ,
b110110 .
b110110 J
b110110 L
1!
#630000
0!
#635000
b111000 -
b111000 K
b110111 ,
b110111 .
b110111 J
b110111 L
1!
#640000
0!
#645000
b111001 -
b111001 K
b111000 ,
b111000 .
b111000 J
b111000 L
1!
#650000
0!
#655000
b111010 -
b111010 K
b111001 ,
b111001 .
b111001 J
b111001 L
1!
#660000
0!
#665000
b111011 -
b111011 K
b111010 ,
b111010 .
b111010 J
b111010 L
1!
#670000
0!
#675000
b111100 -
b111100 K
b111011 ,
b111011 .
b111011 J
b111011 L
1!
#680000
0!
#685000
b111101 -
b111101 K
b111100 ,
b111100 .
b111100 J
b111100 L
1!
#690000
0!
#695000
b111110 -
b111110 K
b111101 ,
b111101 .
b111101 J
b111101 L
1!
#700000
0!
#705000
b111111 -
b111111 K
b111110 ,
b111110 .
b111110 J
b111110 L
1!
#710000
0!
#715000
b1000000 -
b1000000 K
b111111 ,
b111111 .
b111111 J
b111111 L
1!
#720000
0!
#725000
b1000001 -
b1000001 K
b1000000 ,
b1000000 .
b1000000 J
b1000000 L
1!
#730000
0!
#735000
b1000010 -
b1000010 K
b1000001 ,
b1000001 .
b1000001 J
b1000001 L
1!
#740000
0!
#745000
b1000011 -
b1000011 K
b1000010 ,
b1000010 .
b1000010 J
b1000010 L
1!
#750000
0!
#755000
b1000100 -
b1000100 K
b1000011 ,
b1000011 .
b1000011 J
b1000011 L
1!
#760000
0!
#765000
b1000101 -
b1000101 K
b1000100 ,
b1000100 .
b1000100 J
b1000100 L
1!
#770000
0!
#775000
b1000110 -
b1000110 K
b1000101 ,
b1000101 .
b1000101 J
b1000101 L
1!
#780000
0!
#785000
b1000111 -
b1000111 K
b1000110 ,
b1000110 .
b1000110 J
b1000110 L
1!
#790000
0!
#795000
b1001000 -
b1001000 K
b1000111 ,
b1000111 .
b1000111 J
b1000111 L
1!
#800000
0!
#805000
b1001001 -
b1001001 K
b1001000 ,
b1001000 .
b1001000 J
b1001000 L
1!
#810000
0!
#815000
b1001010 -
b1001010 K
b1001001 ,
b1001001 .
b1001001 J
b1001001 L
1!
#820000
0!
#825000
b1001011 -
b1001011 K
b1001010 ,
b1001010 .
b1001010 J
b1001010 L
1!
#830000
0!
#835000
b1001100 -
b1001100 K
b1001011 ,
b1001011 .
b1001011 J
b1001011 L
1!
#840000
0!
#845000
b1001101 -
b1001101 K
b1001100 ,
b1001100 .
b1001100 J
b1001100 L
1!
#850000
0!
#855000
b1001110 -
b1001110 K
b1001101 ,
b1001101 .
b1001101 J
b1001101 L
1!
#860000
0!
#865000
b1001111 -
b1001111 K
b1001110 ,
b1001110 .
b1001110 J
b1001110 L
1!
#870000
0!
#875000
b1010000 -
b1010000 K
b1001111 ,
b1001111 .
b1001111 J
b1001111 L
1!
#880000
0!
#885000
b1010001 -
b1010001 K
b1010000 ,
b1010000 .
b1010000 J
b1010000 L
1!
#890000
0!
#895000
b1010010 -
b1010010 K
b1010001 ,
b1010001 .
b1010001 J
b1010001 L
1!
#900000
0!
#905000
b1010011 -
b1010011 K
b1010010 ,
b1010010 .
b1010010 J
b1010010 L
1!
#910000
0!
#915000
b1010100 -
b1010100 K
b1010011 ,
b1010011 .
b1010011 J
b1010011 L
1!
#920000
0!
#925000
b1010101 -
b1010101 K
b1010100 ,
b1010100 .
b1010100 J
b1010100 L
1!
#930000
0!
#935000
b1010110 -
b1010110 K
b1010101 ,
b1010101 .
b1010101 J
b1010101 L
1!
#940000
0!
#945000
b1010111 -
b1010111 K
b1010110 ,
b1010110 .
b1010110 J
b1010110 L
1!
#950000
0!
#955000
b1011000 -
b1011000 K
b1010111 ,
b1010111 .
b1010111 J
b1010111 L
1!
#960000
0!
#965000
b1011001 -
b1011001 K
b1011000 ,
b1011000 .
b1011000 J
b1011000 L
1!
#970000
0!
#975000
b1011010 -
b1011010 K
b1011001 ,
b1011001 .
b1011001 J
b1011001 L
1!
#980000
0!
#985000
b1011011 -
b1011011 K
b1011010 ,
b1011010 .
b1011010 J
b1011010 L
1!
#990000
0!
#995000
b1011100 -
b1011100 K
b1011011 ,
b1011011 .
b1011011 J
b1011011 L
1!
#1000000
0!
#1005000
b1011101 -
b1011101 K
b1011100 ,
b1011100 .
b1011100 J
b1011100 L
1!
#1010000
0!
#1015000
b1011110 -
b1011110 K
b1011101 ,
b1011101 .
b1011101 J
b1011101 L
1!
#1020000
0!
#1025000
b1011111 -
b1011111 K
b1011110 ,
b1011110 .
b1011110 J
b1011110 L
1!
#1030000
0!
#1035000
b1100000 -
b1100000 K
b1011111 ,
b1011111 .
b1011111 J
b1011111 L
1!
#1040000
0!
#1045000
b1100001 -
b1100001 K
b1100000 ,
b1100000 .
b1100000 J
b1100000 L
1!
#1050000
0!
#1055000
b1100010 -
b1100010 K
b1100001 ,
b1100001 .
b1100001 J
b1100001 L
1!
#1060000
0!
#1065000
b1100011 -
b1100011 K
b1100010 ,
b1100010 .
b1100010 J
b1100010 L
1!
#1070000
0!
#1075000
b1100100 -
b1100100 K
b1100011 ,
b1100011 .
b1100011 J
b1100011 L
1!
#1080000
0!
#1085000
b1100101 -
b1100101 K
b1100100 ,
b1100100 .
b1100100 J
b1100100 L
1!
#1090000
0!
